log_labeler/__init__.py
log_labeler/decorators.py
log_labeler/encoders.py
log_labeler/filters.py
log_labeler/middleware.py
log_labeler/utils.py
log_labeler/__pycache__/__init__.cpython-37.pyc
log_labeler/__pycache__/decorators.cpython-37.pyc
log_labeler/__pycache__/filters.cpython-37.pyc
log_labeler/__pycache__/middleware.cpython-37.pyc
log_labeler/__pycache__/utils.cpython-37.pyc
django_log_labeler-1.2.5.dist-info/METADATA
django_log_labeler-1.2.5.dist-info/WHEEL
django_log_labeler-1.2.5.dist-info/top_level.txt
django_log_labeler-1.2.5.dist-info/RECORD
