Metadata-Version: 2.1
Name: django-log-labeler
Version: 1.2.5
Summary: Django middleware and log filter to attach a unique ID to every log message generated as part of a request
Home-page: https://psbl102zatcrh.vodacom.corp/nimble-backend/Vodacom-Django-Log-Labeler/
Author: Hermann
Author-email: hermann.ntsamo@vcontractor.co.za
License: BSD
Platform: UNKNOWN
Requires-Dist: django (>=1.9.2)
Requires-Dist: requests (>=2.22.0)
Requires-Dist: twine (==3.1.1)
